{
  "_class": "rectangle",
  "booleanOperation": -1,
  "clippingMaskMode": 0,
  "do_objectID": "3A9D15C3-E07B-4472-8910-514F1A76FC0A",
  "edited": true,
  "exportOptions": {
    "_class": "exportOptions",
    "exportFormats": [
    ],
    "includedLayerIds": [
    ],
    "layerOptions": 0,
    "shouldTrim": false
  },
  "fixedRadius": 0,
  "frame": {
    "_class": "rect",
    "constrainProportions": false,
    "height": 11.90584198030829,
    "width": 9.233301750054176,
    "x": 0.7166874077261127,
    "y": 0
  },
  "hasClippingMask": true,
  "hasConvertedToNewRoundCorners": true,
  "isClosed": true,
  "isFixedToViewport": false,
  "isFlippedHorizontal": false,
  "isFlippedVertical": false,
  "isLocked": false,
  "isVisible": true,
  "layerListExpandedType": 0,
  "name": "Mask",
  "nameIsFixed": false,
  "needsConvertionToNewRoundCorners": false,
  "pointRadiusBehaviour": 0,
  "points": [
    {
      "_class": "curvePoint",
      "cornerRadius": 1.333333333333333,
      "curveFrom": "{0.066784985728818233, 0}",
      "curveMode": 1,
      "curveTo": "{0.066784985728818233, 0}",
      "hasCurveFrom": false,
      "hasCurveTo": false,
      "point": "{0.030683779209552356, 0}"
    },
    {
      "_class": "curvePoint",
      "cornerRadius": 1.333333333333333,
      "curveFrom": "{0.93321394219101328, 0}",
      "curveMode": 1,
      "curveTo": "{0.93321394219101328, 0}",
      "hasCurveFrom": false,
      "hasCurveTo": false,
      "point": "{0.96931514871027169, 0}"
    },
    {
      "_class": "curvePoint",
      "cornerRadius": 1.333333333333333,
      "curveFrom": "{0.90531541866343546, 0.72793395721200804}",
      "curveMode": 1,
      "curveTo": "{1.005416355229529, 0.72793395721200804}",
      "hasCurveFrom": false,
      "hasCurveTo": false,
      "point": "{1.005416355229529, 0.72793395721200804}"
    },
    {
      "_class": "curvePoint",
      "cornerRadius": 2,
      "curveFrom": "{0.39606747487908273, 1.0639034759252426}",
      "curveMode": 1,
      "curveTo": "{0.5886072429817929, 1.0639034759252426}",
      "hasCurveFrom": false,
      "hasCurveTo": false,
      "point": "{0.49999946395991579, 1.0639034759252426}"
    },
    {
      "_class": "curvePoint",
      "cornerRadius": 1.333333333333333,
      "curveFrom": "{-0.0054174273096980145, 0.72793395721200804}",
      "curveMode": 1,
      "curveTo": "{0.087021404226917981, 0.72793395721200804}",
      "hasCurveFrom": false,
      "hasCurveTo": false,
      "point": "{-0.0054174273096980145, 0.72793395721200804}"
    }
  ],
  "resizingConstraint": 63,
  "resizingType": 0,
  "rotation": 0,
  "shouldBreakMaskChain": false,
  "style": {
    "_class": "style",
    "blur": {
      "_class": "blur",
      "center": "{0.5, 0.5}",
      "isEnabled": false,
      "motionAngle": 0,
      "radius": 13.33333333333333,
      "saturation": 1,
      "type": 0
    },
    "borderOptions": {
      "_class": "borderOptions",
      "dashPattern": [
      ],
      "isEnabled": true,
      "lineCapStyle": 0,
      "lineJoinStyle": 0
    },
    "borders": [
      {
        "_class": "border",
        "color": {
          "_class": "color",
          "alpha": 1,
          "blue": 1,
          "green": 1,
          "red": 1
        },
        "contextSettings": {
          "_class": "graphicsContextSettings",
          "blendMode": 0,
          "opacity": 1
        },
        "fillType": 0,
        "gradient": {
          "_class": "gradient",
          "elipseLength": 1,
          "from": "{0.5, 0}",
          "gradientType": 0,
          "stops": [
            {
              "_class": "gradientStop",
              "color": {
                "_class": "color",
                "alpha": 1,
                "blue": 1,
                "green": 1,
                "red": 1
              },
              "position": 0
            },
            {
              "_class": "gradientStop",
              "color": {
                "_class": "color",
                "alpha": 1,
                "blue": 0.9411764705882353,
                "green": 0.9411764705882353,
                "red": 0.9411764705882353
              },
              "position": 1
            }
          ],
          "to": "{0.5, 1}"
        },
        "isEnabled": true,
        "position": 2,
        "thickness": 1.333333333333333
      }
    ],
    "colorControls": {
      "_class": "colorControls",
      "brightness": 0,
      "contrast": 1,
      "hue": 0,
      "isEnabled": false,
      "saturation": 1
    },
    "contextSettings": {
      "_class": "graphicsContextSettings",
      "blendMode": 0,
      "opacity": 1
    },
    "do_objectID": "4E03725E-1151-411F-AB53-1D7D79C4ECB9",
    "endMarkerType": 0,
    "fills": [
      {
        "_class": "fill",
        "color": {
          "_class": "color",
          "alpha": 1,
          "blue": 0.2666666666666664,
          "green": 0.2156862745098039,
          "red": 0.9686274509803922
        },
        "contextSettings": {
          "_class": "graphicsContextSettings",
          "blendMode": 0,
          "opacity": 1
        },
        "fillType": 0,
        "gradient": {
          "_class": "gradient",
          "elipseLength": 1,
          "from": "{0.5, 0}",
          "gradientType": 0,
          "stops": [
            {
              "_class": "gradientStop",
              "color": {
                "_class": "color",
                "alpha": 1,
                "blue": 0.2669587887691228,
                "green": 0.214988033263485,
                "red": 0.9685639880952381
              },
              "position": 0
            },
            {
              "_class": "gradientStop",
              "color": {
                "_class": "color",
                "alpha": 1,
                "blue": 0.1843137254901958,
                "green": 0.1294117647058823,
                "red": 0.9254901960784314
              },
              "position": 1
            }
          ],
          "to": "{0.5, 1}"
        },
        "isEnabled": true,
        "noiseIndex": 0,
        "noiseIntensity": 0,
        "patternFillType": 0,
        "patternTileScale": 1
      }
    ],
    "innerShadows": [
    ],
    "miterLimit": 10,
    "shadows": [
      {
        "_class": "shadow",
        "blurRadius": 0,
        "color": {
          "_class": "color",
          "alpha": 0.06,
          "blue": 0,
          "green": 0,
          "red": 0
        },
        "contextSettings": {
          "_class": "graphicsContextSettings",
          "blendMode": 1,
          "opacity": 1
        },
        "isEnabled": false,
        "offsetX": 0,
        "offsetY": 1,
        "spread": 0
      }
    ],
    "startMarkerType": 0,
    "windingRule": 1
  }
}