{
  "_class": "group",
  "do_objectID": "E506BA13-4721-4CE0-BBE7-6720AD914176",
  "exportOptions": {
    "_class": "exportOptions",
    "exportFormats": [
    ],
    "includedLayerIds": [
    ],
    "layerOptions": 0,
    "shouldTrim": false
  },
  "frame": {
    "_class": "rect",
    "constrainProportions": false,
    "height": 86,
    "width": 240,
    "x": 16,
    "y": 52
  },
  "hasClickThrough": false,
  "isFlippedHorizontal": false,
  "isFlippedVertical": false,
  "isLocked": false,
  "isVisible": true,
  "layerListExpandedType": 0,
  "layers": [
    {
      "class": "text",
      "id": "A7B4118E-676A-45D8-965D-B4D71044A406"
    },
    {
      "class": "text",
      "id": "AC073213-A112-43F0-8EE8-63CF1301201F"
    },
    {
      "class": "text",
      "id": "780D4A83-07FE-4FA1-B76B-E86AF514A32F"
    },
    {
      "class": "text",
      "id": "1463EAEE-3055-4AEC-A4DE-13871F79FCE2"
    }
  ],
  "name": "Group 15",
  "nameIsFixed": false,
  "resizingConstraint": 63,
  "resizingType": 0,
  "rotation": 0,
  "shouldBreakMaskChain": false,
  "style": {
    "_class": "style",
    "endDecorationType": 0,
    "miterLimit": 10,
    "startDecorationType": 0
  }
}