{
  "_class": "group",
  "do_objectID": "133F2519-DFE8-4B96-8883-D521F9D5A06D",
  "exportOptions": {
    "_class": "exportOptions",
    "exportFormats": [
    ],
    "includedLayerIds": [
    ],
    "layerOptions": 0,
    "shouldTrim": false
  },
  "frame": {
    "_class": "rect",
    "constrainProportions": false,
    "height": 48,
    "width": 41,
    "x": 5.578124999999998,
    "y": 1.638888888888887
  },
  "hasClickThrough": false,
  "isFlippedHorizontal": false,
  "isFlippedVertical": false,
  "isLocked": false,
  "isVisible": true,
  "layerListExpandedType": 0,
  "layers": [
    {
      "class": "shapeGroup",
      "id": "661FBFAC-6B8E-43BB-BFE9-929E68F0EFD0"
    },
    {
      "class": "group",
      "id": "6FF8470D-954D-4FB3-9672-CE5BBE09908B"
    }
  ],
  "name": "Page 1 Copy 5",
  "nameIsFixed": false,
  "resizingConstraint": 63,
  "resizingType": 0,
  "rotation": 0,
  "shouldBreakMaskChain": false,
  "style": {
    "_class": "style",
    "endDecorationType": 0,
    "miterLimit": 10,
    "startDecorationType": 0
  }
}