{
  "_class": "shapePath",
  "booleanOperation": -1,
  "do_objectID": "BEBE7048-38AC-4F26-A15E-52949EF00A22",
  "edited": true,
  "exportOptions": {
    "_class": "exportOptions",
    "exportFormats": [
    ],
    "includedLayerIds": [
    ],
    "layerOptions": 0,
    "shouldTrim": false
  },
  "frame": {
    "_class": "rect",
    "constrainProportions": false,
    "height": 5.682143446645249,
    "width": 2.137765735264067,
    "x": 0,
    "y": 0
  },
  "isFlippedHorizontal": false,
  "isFlippedVertical": false,
  "isLocked": false,
  "isVisible": true,
  "layerListExpandedType": 0,
  "name": "Path",
  "nameIsFixed": false,
  "path": {
    "_class": "path",
    "isClosed": false,
    "pointRadiusBehaviour": 1,
    "points": [
      {
        "_class": "curvePoint",
        "cornerRadius": 0,
        "curveFrom": "{0.31425285892663124, 0.97357992073976185}",
        "curveMode": 4,
        "curveTo": "{0.31425285892663124, 0.94095112285336824}",
        "hasCurveFrom": true,
        "hasCurveTo": false,
        "point": "{0.31425285892663124, 0.94095112285336824}"
      },
      {
        "_class": "curvePoint",
        "cornerRadius": 0,
        "curveFrom": "{0.070224102553436932, 1}",
        "curveMode": 2,
        "curveTo": "{0.24367763586042668, 1}",
        "hasCurveFrom": true,
        "hasCurveTo": true,
        "point": "{0.15695086920693183, 1}"
      },
      {
        "_class": "curvePoint",
        "cornerRadius": 0,
        "curveFrom": "{0, 0.84200792602377739}",
        "curveMode": 3,
        "curveTo": "{0, 0.97357992073976185}",
        "hasCurveFrom": true,
        "hasCurveTo": true,
        "point": "{0, 0.94095112285336824}"
      },
      {
        "_class": "curvePoint",
        "cornerRadius": 0,
        "curveFrom": "{0.075139789732177303, 0.75284015852047526}",
        "curveMode": 4,
        "curveTo": "{0.0010533615383015976, 0.79114927344781993}",
        "hasCurveFrom": false,
        "hasCurveTo": true,
        "point": "{0.075139789732177303, 0.75284015852047526}"
      },
      {
        "_class": "curvePoint",
        "cornerRadius": 0,
        "curveFrom": "{0.16362215894950902, 0.70673712021135981}",
        "curveMode": 4,
        "curveTo": "{0.074437548706643319, 0.75284015852047526}",
        "hasCurveFrom": true,
        "hasCurveTo": false,
        "point": "{0.074437548706643319, 0.75284015852047526}"
      },
      {
        "_class": "curvePoint",
        "cornerRadius": 0,
        "curveFrom": "{0.59620263067868184, 0.70449141347424016}",
        "curveMode": 3,
        "curveTo": "{0.27914080764991217, 0.70449141347424016}",
        "hasCurveFrom": true,
        "hasCurveTo": true,
        "point": "{0.50561353838474821, 0.70449141347424016}"
      },
      {
        "_class": "curvePoint",
        "cornerRadius": 0,
        "curveFrom": "{0.68187603579387512, 0.65416116248348721}",
        "curveMode": 4,
        "curveTo": "{0.64957294861929316, 0.68692206076618167}",
        "hasCurveFrom": true,
        "hasCurveTo": true,
        "point": "{0.67204466143639308, 0.66433289299867848}"
      },
      {
        "_class": "curvePoint",
        "cornerRadius": 0,
        "curveFrom": "{0.68749396399814944, 0.62034346103038285}",
        "curveMode": 4,
        "curveTo": "{0.68714284348538313, 0.64293262879788604}",
        "hasCurveFrom": true,
        "hasCurveTo": true,
        "point": "{0.68714284348538313, 0.63157199471598402}"
      },
      {
        "_class": "curvePoint",
        "cornerRadius": 0,
        "curveFrom": "{0.65483975631080116, 0.57873183619550861}",
        "curveMode": 4,
        "curveTo": "{0.68222715630664266, 0.60898282694848072}",
        "hasCurveFrom": true,
        "hasCurveTo": true,
        "point": "{0.67274690246192836, 0.5981505944517832}"
      },
      {
        "_class": "curvePoint",
        "cornerRadius": 0,
        "curveFrom": "{0.4845463076187162, 0.56380449141347433}",
        "curveMode": 3,
        "curveTo": "{0.61972770503408336, 0.56380449141347433}",
        "hasCurveFrom": true,
        "hasCurveTo": true,
        "point": "{0.57162419478497872, 0.56380449141347433}"
      },
      {
        "_class": "curvePoint",
        "cornerRadius": 0,
        "curveFrom": "{0.41432220506527928, 0.50462351387054161}",
        "curveMode": 4,
        "curveTo": "{0.41432220506527928, 0.53738441215323618}",
        "hasCurveFrom": false,
        "hasCurveTo": true,
        "point": "{0.41432220506527928, 0.50462351387054161}"
      },
      {
        "_class": "curvePoint",
        "cornerRadius": 0,
        "curveFrom": "{0.41432220506527928, 0.026552179656539037}",
        "curveMode": 4,
        "curveTo": "{0.41432220506527928, 0.05904887714663086}",
        "hasCurveFrom": true,
        "hasCurveTo": false,
        "point": "{0.41432220506527928, 0.05904887714663086}"
      },
      {
        "_class": "curvePoint",
        "cornerRadius": 0,
        "curveFrom": "{0.65799984092570596, 0}",
        "curveMode": 2,
        "curveTo": "{0.4845463076187162, 0}",
        "hasCurveFrom": true,
        "hasCurveTo": true,
        "point": "{0.57162419478497872, 0}"
      },
      {
        "_class": "curvePoint",
        "cornerRadius": 0,
        "curveFrom": "{0.72857506399191052, 0.05904887714663086}",
        "curveMode": 4,
        "curveTo": "{0.72857506399191052, 0.026552179656539037}",
        "hasCurveFrom": false,
        "hasCurveTo": true,
        "point": "{0.72857506399191052, 0.05904887714663086}"
      },
      {
        "_class": "curvePoint",
        "cornerRadius": 0,
        "curveFrom": "{0.84584931525615048, 0.47516512549537571}",
        "curveMode": 4,
        "curveTo": "{0.72857506399191052, 0.45693527080581187}",
        "hasCurveFrom": true,
        "hasCurveTo": false,
        "point": "{0.72857506399191052, 0.45693527080581187}"
      },
      {
        "_class": "curvePoint",
        "cornerRadius": 0,
        "curveFrom": "{0.99015984600346441, 0.58229854689564087}",
        "curveMode": 3,
        "curveTo": "{0.92730927421813736, 0.51387054161162493}",
        "hasCurveFrom": true,
        "hasCurveTo": true,
        "point": "{0.96979485626296769, 0.55984147952443852}"
      },
      {
        "_class": "curvePoint",
        "cornerRadius": 0,
        "curveFrom": "{0.99964009984817748, 0.65693527080581227}",
        "curveMode": 2,
        "curveTo": "{1.0003423408737127, 0.60713342140026372}",
        "hasCurveFrom": true,
        "hasCurveTo": true,
        "point": "{0.99999122036094512, 0.63210039630118842}"
      },
      {
        "_class": "curvePoint",
        "cornerRadius": 0,
        "curveFrom": "{0.90027299473506472, 0.7710700132100391}",
        "curveMode": 3,
        "curveTo": "{0.98840424343962874, 0.68216644649933877}",
        "hasCurveFrom": true,
        "hasCurveTo": true,
        "point": "{0.96523028959699364, 0.70554821664464906}"
      },
      {
        "_class": "curvePoint",
        "cornerRadius": 0,
        "curveFrom": "{0.38623256404390377, 0.82272126816380375}",
        "curveMode": 3,
        "curveTo": "{0.75104677680901044, 0.82272126816380375}",
        "hasCurveFrom": true,
        "hasCurveTo": true,
        "point": "{0.50561353838474821, 0.82272126816380375}"
      },
      {
        "_class": "curvePoint",
        "cornerRadius": 0,
        "curveFrom": "{0.328648799950086, 0.82192866578599655}",
        "curveMode": 4,
        "curveTo": "{0.33005328200115519, 0.82126816380449119}",
        "hasCurveFrom": false,
        "hasCurveTo": true,
        "point": "{0.328648799950086, 0.82192866578599655}"
      },
      {
        "_class": "curvePoint",
        "cornerRadius": 0,
        "curveFrom": "{0.31460397943939883, 0.82906208718626107}",
        "curveMode": 4,
        "curveTo": "{0.32829767943731836, 0.82192866578599655}",
        "hasCurveFrom": true,
        "hasCurveTo": false,
        "point": "{0.32829767943731836, 0.82192866578599655}"
      },
      {
        "_class": "curvePoint",
        "cornerRadius": 0,
        "curveFrom": "{0.31425285892663124, 0.94095112285336824}",
        "curveMode": 4,
        "curveTo": "{0.31425285892663124, 0.86684280052840124}",
        "hasCurveFrom": false,
        "hasCurveTo": true,
        "point": "{0.31425285892663124, 0.94095112285336824}"
      }
    ]
  },
  "resizingConstraint": 63,
  "resizingType": 0,
  "rotation": 0,
  "shouldBreakMaskChain": false
}