{
  "_class": "group",
  "do_objectID": "E32F9DC3-8980-41F7-AA6D-BB1416880F91",
  "exportOptions": {
    "_class": "exportOptions",
    "exportFormats": [
    ],
    "includedLayerIds": [
    ],
    "layerOptions": 0,
    "shouldTrim": false
  },
  "frame": {
    "_class": "rect",
    "constrainProportions": false,
    "height": 18,
    "width": 224,
    "x": 16,
    "y": 636
  },
  "hasClickThrough": false,
  "isFlippedHorizontal": false,
  "isFlippedVertical": false,
  "isLocked": false,
  "isVisible": true,
  "layerListExpandedType": 0,
  "layers": [
    {
      "class": "text",
      "id": "33636031-9989-453F-BCAD-E70A8AC78F74"
    },
    {
      "class": "text",
      "id": "5E34FD6A-2CDD-4934-872C-5D413D81770A"
    },
    {
      "class": "group",
      "id": "48DB21B8-E835-4E7D-A069-907AB8E15353"
    },
    {
      "class": "group",
      "id": "50E16A51-7177-4D25-AD41-CCB84C1B02DE"
    }
  ],
  "name": "Group 3",
  "nameIsFixed": false,
  "resizingConstraint": 63,
  "resizingType": 0,
  "rotation": 0,
  "shouldBreakMaskChain": false,
  "style": {
    "_class": "style",
    "endDecorationType": 0,
    "miterLimit": 10,
    "startDecorationType": 0
  }
}