{
  "_class": "group",
  "do_objectID": "54E6B74D-9E87-4C8D-8470-CECD83F91728",
  "exportOptions": {
    "_class": "exportOptions",
    "exportFormats": [
    ],
    "includedLayerIds": [
    ],
    "layerOptions": 0,
    "shouldTrim": false
  },
  "frame": {
    "_class": "rect",
    "constrainProportions": false,
    "height": 296,
    "width": 168,
    "x": 552,
    "y": 0
  },
  "hasClickThrough": false,
  "isFlippedHorizontal": false,
  "isFlippedVertical": false,
  "isLocked": false,
  "isVisible": true,
  "layerListExpandedType": 1,
  "layers": [
    {
      "class": "group",
      "id": "039C32D7-6065-4872-8D43-12150D7F8370"
    },
    {
      "class": "text",
      "id": "378B5B95-7EDE-4EF8-9CC6-B66326C4E033"
    },
    {
      "class": "text",
      "id": "8BBB08A8-C5CE-46E5-BF33-7DE26EA001A6"
    },
    {
      "class": "text",
      "id": "34BA00F4-5B6F-4358-B5F3-185004554B2B"
    },
    {
      "class": "text",
      "id": "A98DC4B7-FB30-4D7C-99F6-6D9557382474"
    },
    {
      "class": "text",
      "id": "51B84C64-B522-49E2-B91F-1F596459FD7B"
    },
    {
      "class": "text",
      "id": "03627FBB-8A98-409D-8E03-3667F94D06B4"
    },
    {
      "class": "text",
      "id": "EB101115-A8CD-434B-BF61-3783016F1109"
    },
    {
      "class": "text",
      "id": "C428EDA9-4369-45D7-B92D-DEDCD4C2FAF1"
    },
    {
      "class": "text",
      "id": "E6F7F818-A9A5-45C9-BD88-99E40B6AD13E"
    },
    {
      "class": "text",
      "id": "4E14E231-22C5-4AA7-AAB4-EB97319966F0"
    },
    {
      "class": "text",
      "id": "B29A0071-AB11-4162-A36D-03B4C49CA4B8"
    },
    {
      "class": "text",
      "id": "BE819F9A-ECE9-4F84-A61A-24C086290DE5"
    },
    {
      "class": "text",
      "id": "02406F37-B2EF-40D6-874B-20D3632D77D2"
    },
    {
      "class": "group",
      "id": "2210339A-70D6-48C5-A24B-0A584C195490"
    },
    {
      "class": "bitmap",
      "id": "C63758E5-DE8A-4E2A-A82B-0B4D26C9385B"
    },
    {
      "class": "shapeGroup",
      "id": "66AFA1E0-84E6-45C8-8EE8-BFFD7E1EDF0B"
    },
    {
      "class": "text",
      "id": "CE3FB9FA-C2C3-43A8-B675-7FAB7E87B28E"
    },
    {
      "class": "group",
      "id": "A353A0E9-24D2-40E3-869F-09B58A6F220D"
    }
  ],
  "name": "Card giocatore Copy 2",
  "nameIsFixed": true,
  "resizingConstraint": 63,
  "resizingType": 0,
  "rotation": 0,
  "shouldBreakMaskChain": false,
  "style": {
    "_class": "style",
    "endDecorationType": 0,
    "miterLimit": 10,
    "startDecorationType": 0
  }
}