{
  "_class": "rectangle",
  "booleanOperation": -1,
  "clippingMaskMode": 0,
  "do_objectID": "86E424C3-9C7C-4D5A-A618-10BD3272BAD2",
  "edited": true,
  "exportOptions": {
    "_class": "exportOptions",
    "exportFormats": [
    ],
    "includedLayerIds": [
    ],
    "layerOptions": 0,
    "shouldTrim": false
  },
  "fixedRadius": 0,
  "frame": {
    "_class": "rect",
    "constrainProportions": false,
    "height": 4,
    "width": 6.666666666666666,
    "x": 10.66666666666669,
    "y": 8
  },
  "hasClippingMask": false,
  "hasConvertedToNewRoundCorners": true,
  "isClosed": true,
  "isFixedToViewport": false,
  "isFlippedHorizontal": false,
  "isFlippedVertical": false,
  "isLocked": false,
  "isVisible": true,
  "layerListExpandedType": 0,
  "name": "Rectangle 129",
  "nameIsFixed": false,
  "needsConvertionToNewRoundCorners": false,
  "pointRadiusBehaviour": 0,
  "points": [
    {
      "_class": "curvePoint",
      "cornerRadius": 0.6666666666666666,
      "curveFrom": "{0.091011868990384631, 0.10112429887820513}",
      "curveMode": 1,
      "curveTo": "{0, 0}",
      "hasCurveFrom": false,
      "hasCurveTo": false,
      "point": "{0, 0}"
    },
    {
      "_class": "curvePoint",
      "cornerRadius": 0.3333333333333333,
      "curveFrom": "{0.26363900991586542, 0.070710011017628221}",
      "curveMode": 1,
      "curveTo": "{0.19096444936899037, -0.010039500701121806}",
      "hasCurveFrom": false,
      "hasCurveTo": false,
      "point": "{0.20000000000000001, 0}"
    },
    {
      "_class": "curvePoint",
      "cornerRadius": 0,
      "curveFrom": "{0.29999999999999999, 0.33333333333333331}",
      "curveMode": 1,
      "curveTo": "{0.23636099008413464, 0.26262332231570512}",
      "hasCurveFrom": false,
      "hasCurveTo": false,
      "point": "{0.29999999999999999, 0.33333333333333331}"
    },
    {
      "_class": "curvePoint",
      "cornerRadius": 0,
      "curveFrom": "{0.59999999999999998, 0}",
      "curveMode": 2,
      "curveTo": "{0.40986612242390336, 0}",
      "hasCurveFrom": true,
      "hasCurveTo": true,
      "point": "{0.5, 0}"
    },
    {
      "_class": "curvePoint",
      "cornerRadius": 0,
      "curveFrom": "{0.73063307542067313, 0.29929658286591881}",
      "curveMode": 1,
      "curveTo": "{0.63744303385416656, 0.33333333333333331}",
      "hasCurveFrom": false,
      "hasCurveTo": false,
      "point": "{0.69999999999999996, 0.33333333333333331}"
    },
    {
      "_class": "curvePoint",
      "cornerRadius": 0.3333333333333333,
      "curveFrom": "{0.84204148512620203, -0.046712761251335583}",
      "curveMode": 1,
      "curveTo": "{0.76936692457932709, 0.034036750467414556}",
      "hasCurveFrom": false,
      "hasCurveTo": false,
      "point": "{0.80000000000000004, 0}"
    },
    {
      "_class": "curvePoint",
      "cornerRadius": 0.6666666666666666,
      "curveFrom": "{1, 0}",
      "curveMode": 1,
      "curveTo": "{0.87598219651442299, 0.13779755942841879}",
      "hasCurveFrom": false,
      "hasCurveTo": false,
      "point": "{1, 0}"
    },
    {
      "_class": "curvePoint",
      "cornerRadius": 0.6666666666666666,
      "curveFrom": "{0.87278645833333324, 1}",
      "curveMode": 1,
      "curveTo": "{1, 1}",
      "hasCurveFrom": false,
      "hasCurveTo": false,
      "point": "{1, 1}"
    },
    {
      "_class": "curvePoint",
      "cornerRadius": 0,
      "curveFrom": "{0.68641601562499999, 0.71194661458333341}",
      "curveMode": 1,
      "curveTo": "{0.84557291666666656, 0.66666666666666663}",
      "hasCurveFrom": false,
      "hasCurveTo": false,
      "point": "{0.69999999999999996, 0.66666666666666663}"
    },
    {
      "_class": "curvePoint",
      "cornerRadius": 0,
      "curveFrom": "{0.59535685221354173, 0.68214382595486101}",
      "curveMode": 1,
      "curveTo": "{0.61358398437499984, 0.62138671874999996}",
      "hasCurveFrom": false,
      "hasCurveTo": false,
      "point": "{0.59999999999999998, 0.66666666666666663}"
    },
    {
      "_class": "curvePoint",
      "cornerRadius": 0.6666666666666666,
      "curveFrom": "{0.55206054687500006, 0.96005045572916659}",
      "curveMode": 1,
      "curveTo": "{0.64996175130208333, 0.83346082899305562}",
      "hasCurveFrom": false,
      "hasCurveTo": false,
      "point": "{0.59999999999999998, 1}"
    },
    {
      "_class": "curvePoint",
      "cornerRadius": 0.6666666666666666,
      "curveFrom": "{0.35391845703125002, 0.84639485677083337}",
      "curveMode": 1,
      "curveTo": "{0.44793945312500016, 1.0399495442708333}",
      "hasCurveFrom": false,
      "hasCurveTo": false,
      "point": "{0.40000000000000002, 1}"
    },
    {
      "_class": "curvePoint",
      "cornerRadius": 0,
      "curveFrom": "{0.38253580729166597, 0.60845269097222243}",
      "curveMode": 1,
      "curveTo": "{0.40076293945312508, 0.66920979817708337}",
      "hasCurveFrom": false,
      "hasCurveTo": false,
      "point": "{0.40000000000000002, 0.66666666666666663}"
    },
    {
      "_class": "curvePoint",
      "cornerRadius": 0,
      "curveFrom": "{0.092643229166666563, 0.66666666666666663}",
      "curveMode": 1,
      "curveTo": "{0.31746419270833331, 0.72488064236111105}",
      "hasCurveFrom": false,
      "hasCurveTo": false,
      "point": "{0.29999999999999999, 0.66666666666666663}"
    },
    {
      "_class": "curvePoint",
      "cornerRadius": 0.6666666666666666,
      "curveFrom": "{0, 1}",
      "curveMode": 1,
      "curveTo": "{0.19632161458333328, 1}",
      "hasCurveFrom": false,
      "hasCurveTo": false,
      "point": "{0, 1}"
    }
  ],
  "resizingConstraint": 63,
  "resizingType": 0,
  "rotation": 0,
  "shouldBreakMaskChain": false,
  "style": {
    "_class": "style",
    "blur": {
      "_class": "blur",
      "center": "{0.5, 0.5}",
      "isEnabled": false,
      "motionAngle": 0,
      "radius": 13.33333333333333,
      "saturation": 1,
      "type": 0
    },
    "borderOptions": {
      "_class": "borderOptions",
      "dashPattern": [
      ],
      "isEnabled": true,
      "lineCapStyle": 0,
      "lineJoinStyle": 0
    },
    "borders": [
      {
        "_class": "border",
        "color": {
          "_class": "color",
          "alpha": 1,
          "blue": 0.2742187483224034,
          "green": 0.6570798881701284,
          "red": 0.7750850340136054
        },
        "contextSettings": {
          "_class": "graphicsContextSettings",
          "blendMode": 0,
          "opacity": 1
        },
        "fillType": 0,
        "gradient": {
          "_class": "gradient",
          "elipseLength": 0,
          "from": "{0.5, 0}",
          "gradientType": 0,
          "stops": [
            {
              "_class": "gradientStop",
              "color": {
                "_class": "color",
                "alpha": 1,
                "blue": 1,
                "green": 1,
                "red": 1
              },
              "position": 0
            },
            {
              "_class": "gradientStop",
              "color": {
                "_class": "color",
                "alpha": 1,
                "blue": 0,
                "green": 0,
                "red": 0
              },
              "position": 1
            }
          ],
          "to": "{0.5, 1}"
        },
        "isEnabled": true,
        "position": 1,
        "thickness": 0.6666666666666666
      }
    ],
    "colorControls": {
      "_class": "colorControls",
      "brightness": 0,
      "contrast": 1,
      "hue": 0,
      "isEnabled": false,
      "saturation": 1
    },
    "contextSettings": {
      "_class": "graphicsContextSettings",
      "blendMode": 0,
      "opacity": 1
    },
    "do_objectID": "B9CA8D19-6F84-41CB-BCD1-69BA40CE6C17",
    "endMarkerType": 0,
    "fills": [
      {
        "_class": "fill",
        "color": {
          "_class": "color",
          "alpha": 0.25,
          "blue": 0.1803921568627451,
          "green": 0.7019607843137254,
          "red": 0.9568627450980391
        },
        "contextSettings": {
          "_class": "graphicsContextSettings",
          "blendMode": 0,
          "opacity": 1
        },
        "fillType": 0,
        "gradient": {
          "_class": "gradient",
          "elipseLength": 0,
          "from": "{0.5, 0}",
          "gradientType": 0,
          "stops": [
            {
              "_class": "gradientStop",
              "color": {
                "_class": "color",
                "alpha": 1,
                "blue": 1,
                "green": 1,
                "red": 1
              },
              "position": 0
            },
            {
              "_class": "gradientStop",
              "color": {
                "_class": "color",
                "alpha": 1,
                "blue": 0,
                "green": 0,
                "red": 0
              },
              "position": 1
            }
          ],
          "to": "{0.5, 1}"
        },
        "isEnabled": true,
        "noiseIndex": 0,
        "noiseIntensity": 0,
        "patternFillType": 0,
        "patternTileScale": 1
      }
    ],
    "innerShadows": [
    ],
    "miterLimit": 10,
    "shadows": [
    ],
    "startMarkerType": 0,
    "windingRule": 1
  }
}