{
  "_class": "group",
  "do_objectID": "1C437B7F-29B2-465F-81E4-72C3D64D0CA6",
  "exportOptions": {
    "_class": "exportOptions",
    "exportFormats": [
    ],
    "includedLayerIds": [
    ],
    "layerOptions": 0,
    "shouldTrim": false
  },
  "frame": {
    "_class": "rect",
    "constrainProportions": true,
    "height": 16,
    "width": 16,
    "x": 16,
    "y": 84
  },
  "hasClickThrough": false,
  "isFlippedHorizontal": false,
  "isFlippedVertical": false,
  "isLocked": false,
  "isVisible": true,
  "layerListExpandedType": 0,
  "layers": [
    {
      "class": "shapeGroup",
      "id": "3C22C7CA-5FE5-4EB4-A5D5-2AF9D61A2DB3"
    },
    {
      "class": "shapeGroup",
      "id": "5DB3574A-3BF4-442F-9416-B59474D6E333"
    }
  ],
  "name": "ic_live_tv_black_24px",
  "nameIsFixed": false,
  "resizingConstraint": 63,
  "resizingType": 0,
  "rotation": 0,
  "shouldBreakMaskChain": false,
  "style": {
    "_class": "style",
    "endDecorationType": 0,
    "miterLimit": 10,
    "startDecorationType": 0
  }
}